Lab8/Q3/qb.v
module fourtosixteen(a,En,f);
	input [3:0] a;
	input En;
	output [15:0] f;
	wire [3:0] c;
	twotofour stage0(a[3:2],En,c);
	twotofour stage1(a[1:0],~c[0],f[3:0]);
	twotofour stage2(a[1:0],~c[1],f[7:4]);
	twotofour stage3(a[1:0],~c[2],f[11:8]);
	twotofour stage4(a[1:0],~c[3],f[15:12]);
endmodule

module twotofour(a,En,f);	
	input [1:0] a;
	input En;
	output reg [3:0] f;
	always@(a,En)
	begin
		case(En)
		  0: f = 4'b1111;
		  1:
		  begin
		  	case(a)
		  		0:f=4'b1110;
		  		1:f=4'b1101;
		  		2:f=4'b1011;
		  		3:f=4'b0111;
		  	endcase
		  end
		 endcase
	end
endmodule

Lab8/Q3/qb_tb.v
`timescale 1ns/1ns
`include "qb.v"

module qb_tb();
reg [3:0] a;
reg En;
wire [15:0] f;

fourtosixteen f1(a,En,f);
initial
begin
	$dumpfile("qb_tb.vcd");
	$dumpvars(0,qb_tb);
	
	En=1'b1;
	a=4'd0; #20;
	a=4'd1; #20;
	a=4'd2; #20;
	a=4'd3; #20;
	a=4'd4; #20;
	a=4'd5; #20;
	a=4'd6; #20;
	a=4'd7; #20;
	a=4'd8; #20;
	a=4'd9; #20;
	a=4'd10; #20;
	a=4'd11; #20;
	a=4'd12; #20;
	a=4'd13; #20;
	a=4'd14; #20;
	a=4'd15; #20;
	
	$display("Test Complete");
end 
endmodule

Lab8/Q3/qb_tb.vcd
$date
	Thu Oct 20 10:37:17 2022
$end
$version
	Icarus Verilog
$end
$timescale
	1ns
$end
$scope module qb_tb $end
$var wire 16 ! f [15:0] $end
$var reg 1 " En $end
$var reg 4 # a [3:0] $end
$scope module f1 $end
$var wire 1 " En $end
$var wire 4 $ a [3:0] $end
$var wire 16 % f [15:0] $end
$var wire 4 & c [3:0] $end
$scope module stage0 $end
$var wire 1 " En $end
$var wire 2 ' a [1:0] $end
$var reg 4 ( f [3:0] $end
$upscope $end
$scope module stage1 $end
$var wire 1 ) En $end
$var wire 2 * a [1:0] $end
$var reg 4 + f [3:0] $end
$upscope $end
$scope module stage2 $end
$var wire 1 , En $end
$var wire 2 - a [1:0] $end
$var reg 4 . f [3:0] $end
$upscope $end
$scope module stage3 $end
$var wire 1 / En $end
$var wire 2 0 a [1:0] $end
$var reg 4 1 f [3:0] $end
$upscope $end
$scope module stage4 $end
$var wire 1 2 En $end
$var wire 2 3 a [1:0] $end
$var reg 4 4 f [3:0] $end
$upscope $end
$upscope $end
$upscope $end
$enddefinitions $end
#0
$dumpvars
b1111 4
b0 3
02
b1111 1
b0 0
0/
b1111 .
b0 -
0,
b1110 +
b0 *
1)
b1110 (
b0 '
b1110 &
b1111111111111110 %
b0 $
b0 #
1"
b1111111111111110 !
$end
#20
b1111111111111101 !
b1111111111111101 %
b1101 +
b1 *
b1 -
b1 0
b1 3
b1 #
b1 $
#40
b1111111111111011 !
b1111111111111011 %
b1011 +
b10 *
b10 -
b10 0
b10 3
b10 #
b10 $
#60
b1111111111110111 !
b1111111111110111 %
b111 +
b11 *
b11 -
b11 0
b11 3
b11 #
b11 $
#80
b1110 .
1,
0)
b1101 &
b1101 (
b1111111111101111 !
b1111111111101111 %
b1111 +
b1 '
b0 *
b0 -
b0 0
b0 3
b100 #
b100 $
#100
b1111111111011111 !
b1111111111011111 %
b1101 .
b1 *
b1 -
b1 0
b1 3
b101 #
b101 $
#120
b1111111110111111 !
b1111111110111111 %
b1011 .
b10 *
b10 -
b10 0
b10 3
b110 #
b110 $
#140
b1111111101111111 !
b1111111101111111 %
b111 .
b11 *
b11 -
b11 0
b11 3
b111 #
b111 $
#160
b1110 1
1/
0,
b1011 &
b1011 (
b1111111011111111 !
b1111111011111111 %
b1111 .
b10 '
b0 *
b0 -
b0 0
b0 3
b1000 #
b1000 $
#180
b1111110111111111 !
b1111110111111111 %
b1101 1
b1 *
b1 -
b1 0
b1 3
b1001 #
b1001 $
#200
b1111101111111111 !
b1111101111111111 %
b1011 1
b10 *
b10 -
b10 0
b10 3
b1010 #
b1010 $
#220
b1111011111111111 !
b1111011111111111 %
b111 1
b11 *
b11 -
b11 0
b11 3
b1011 #
b1011 $
#240
b1110 4
12
0/
b111 &
b111 (
b1110111111111111 !
b1110111111111111 %
b1111 1
b11 '
b0 *
b0 -
b0 0
b0 3
b1100 #
b1100 $
#260
b1101111111111111 !
b1101111111111111 %
b1101 4
b1 *
b1 -
b1 0
b1 3
b1101 #
b1101 $
#280
b1011111111111111 !
b1011111111111111 %
b1011 4
b10 *
b10 -
b10 0
b10 3
b1110 #
b1110 $
#300
b111111111111111 !
b111111111111111 %
b111 4
b11 *
b11 -
b11 0
b11 3
b1111 #
b1111 $
