Lab1/Q1/Part-2/q1b1.v
module q1b1(a,b,c,d,f);
	input a,b,c,d;
	output f;
	assign x1 = (~((a & b) | c)) & d;
	assign x2 = ((a & b) | c) | d;
	assign f = x1 & x2;
endmodule

Lab1/Q1/Part-2/q1b1_tb.v
`timescale 1ns/1ns
`include "q1b1.v"

module q1b1_tb();
reg a,b,c,d;
wire f;

q1b1 q1b1(a,b,c,d,f);
initial
begin

	$dumpfile("q1b1_tb.vcd");
	$dumpvars(0, q1b1_tb);
	
	a = 1'b0; b = 1'b0; c = 1'b0; d = 1'b0;
	#20;
	
	a = 1'b0; b = 1'b0; c = 1'b0; d = 1'b1;
	#20;
	
	a = 1'b0; b = 1'b0; c = 1'b1; d = 1'b0;
	#20;
	
	a = 1'b0; b = 1'b0; c = 1'b1; d = 1'b1;
	#20;
	
	a = 1'b0; b = 1'b1; c = 1'b0; d = 1'b0;
	#20;
	
	a = 1'b0; b = 1'b1; c = 1'b0; d = 1'b1;
	#20;
	
	a = 1'b0; b = 1'b1; c = 1'b1; d = 1'b0;
	#20;
	
	a = 1'b0; b = 1'b1; c = 1'b1; d = 1'b1;
	#20;
	
	a = 1'b1; b = 1'b0; c = 1'b0; d = 1'b0;
	#20;
	
	a = 1'b1; b = 1'b0; c = 1'b0; d = 1'b1;
	#20;
	
	a = 1'b1; b = 1'b0; c = 1'b1; d = 1'b0;
	#20;
	
	a = 1'b1; b = 1'b0; c = 1'b1; d = 1'b1;
	#20;
	
	a = 1'b1; b = 1'b1; c = 1'b0; d = 1'b0;
	#20;
	
	a = 1'b1; b = 1'b1; c = 1'b0; d = 1'b1;
	#20;
	
	a = 1'b1; b = 1'b1; c = 1'b1; d = 1'b0;
	#20;
	
	a = 1'b1; b = 1'b1; c = 1'b1; d = 1'b1;
	#20;
	
	
	$display("Test complete");
end

endmodule

Lab1/Q1/Part-2/q1b1_tb.vcd
$date
	Thu Aug 25 09:33:24 2022
$end
$version
	Icarus Verilog
$end
$timescale
	1ns
$end
$scope module q1b1_tb $end
$var wire 1 ! f $end
$var reg 1 " a $end
$var reg 1 # b $end
$var reg 1 $ c $end
$var reg 1 % d $end
$scope module q1b1 $end
$var wire 1 " a $end
$var wire 1 # b $end
$var wire 1 $ c $end
$var wire 1 % d $end
$var wire 1 ! f $end
$var wire 1 & x1 $end
$var wire 1 ' x2 $end
$upscope $end
$upscope $end
$enddefinitions $end
#0
$dumpvars
0'
0&
0%
0$
0#
0"
0!
$end
#20
1!
1&
1'
1%
#40
0!
0&
0%
1$
#60
1%
#80
0'
0%
0$
1#
#100
1!
1&
1'
1%
#120
0!
0&
0%
1$
#140
1%
#160
0'
0%
0$
0#
1"
#180
1!
1&
1'
1%
#200
0!
0&
0%
1$
#220
1%
#240
0%
0$
1#
#260
1%
#280
0%
1$
#300
1%
