Lab11/Q5/qb.v
module sync4ud(clk,clear,en,Q);
	input clk,clear,en;
	output [3:0] Q;
	TFF s0(en|~en,clk,clear,Q[0]);
	TFF s1(Q[0]&en|~en&~Q[0],clk,clear,Q[1]);
	TFF s2(Q[1]&Q[0]&en|~Q[1]&~Q[0]&~en,clk,clear,Q[2]);
	TFF s3(Q[0]&Q[1]&Q[2]&en|~Q[0]&~Q[1]&~Q[2]&~en,clk,clear,Q[3]);
endmodule

module TFF(t,clock,resetn,q);
	input t,resetn,clock;
	output reg q;
	always@(negedge clock)
	begin
		if(!resetn)
			q <= 0;
		else
		begin
			if(t)
				q <= ~q;
			else
				q <= q;
		end
	end
endmodule

Lab11/Q5/qb_tb.v
`timescale 1ns/1ns
`include "qb.v" 
module qb_tb();
reg en,clock,clear; 
wire [3:0] Q;
sync4ud r1(clock,clear,en,Q);
initial
begin
	$dumpfile("qb_tb.vcd");
	$dumpvars(0, qb_tb);
	clock=0;
	forever #10 clock = ~clock;
end
initial begin
	en = 0;
	clear = 0; #20;
	clear = 1; #300;
	en = 1;
	clear = 0; #20;
	clear = 1; #300;
	$display("Test complete");
	$finish;
	
end
endmodule

Lab11/Q5/qb_tb.vcd
$date
	Thu Nov 17 10:57:26 2022
$end
$version
	Icarus Verilog
$end
$timescale
	1ns
$end
$scope module qb_tb $end
$var wire 4 ! Q [3:0] $end
$var reg 1 " clear $end
$var reg 1 # clock $end
$var reg 1 $ en $end
$scope module r1 $end
$var wire 1 " clear $end
$var wire 1 # clk $end
$var wire 1 $ en $end
$var wire 4 % Q [3:0] $end
$scope module s0 $end
$var wire 1 # clock $end
$var wire 1 " resetn $end
$var wire 1 & t $end
$var reg 1 ' q $end
$upscope $end
$scope module s1 $end
$var wire 1 # clock $end
$var wire 1 " resetn $end
$var wire 1 ( t $end
$var reg 1 ) q $end
$upscope $end
$scope module s2 $end
$var wire 1 # clock $end
$var wire 1 " resetn $end
$var wire 1 * t $end
$var reg 1 + q $end
$upscope $end
$scope module s3 $end
$var wire 1 # clock $end
$var wire 1 " resetn $end
$var wire 1 , t $end
$var reg 1 - q $end
$upscope $end
$upscope $end
$upscope $end
$enddefinitions $end
#0
$dumpvars
0-
1,
0+
1*
0)
1(
0'
1&
b0 %
0$
0#
0"
b0 !
$end
#10
1#
#20
0,
0*
0(
1-
1+
1)
b1111 !
b1111 %
1'
0#
1"
#30
1#
#40
1(
b1110 !
b1110 %
0'
0#
#50
1#
#60
0(
0)
b1101 !
b1101 %
1'
0#
#70
1#
#80
1*
1(
b1100 !
b1100 %
0'
0#
#90
1#
#100
0*
0(
0+
1)
b1011 !
b1011 %
1'
0#
#110
1#
#120
1(
b1010 !
b1010 %
0'
0#
#130
1#
#140
0(
0)
b1001 !
b1001 %
1'
0#
#150
1#
#160
1,
1*
1(
b1000 !
b1000 %
0'
0#
#170
1#
#180
0,
0*
0(
0-
1+
1)
b111 !
b111 %
1'
0#
#190
1#
#200
1(
b110 !
b110 %
0'
0#
#210
1#
#220
0(
0)
b101 !
b101 %
1'
0#
#230
1#
#240
1*
1(
b100 !
b100 %
0'
0#
#250
1#
#260
0*
0(
0+
1)
b11 !
b11 %
1'
0#
#270
1#
#280
1(
b10 !
b10 %
0'
0#
#290
1#
#300
0(
0)
b1 !
b1 %
1'
0#
#310
1#
#320
b0 !
b0 %
0'
0(
0#
0"
1$
#330
1#
#340
1(
b1 !
b1 %
1'
0#
1"
#350
1#
#360
0(
0'
b10 !
b10 %
1)
0#
#370
1#
#380
1*
1(
b11 !
b11 %
1'
0#
#390
1#
#400
0*
0,
0(
0'
0)
b100 !
b100 %
1+
0#
#410
1#
#420
1(
b101 !
b101 %
1'
0#
#430
1#
#440
0(
0'
b110 !
b110 %
1)
0#
#450
1#
#460
1,
1*
1(
b111 !
b111 %
1'
0#
#470
1#
#480
0*
0,
0(
0'
0)
0+
b1000 !
b1000 %
1-
0#
#490
1#
#500
1(
b1001 !
b1001 %
1'
0#
#510
1#
#520
0(
0'
b1010 !
b1010 %
1)
0#
#530
1#
#540
1*
1(
b1011 !
b1011 %
1'
0#
#550
1#
#560
0*
0,
0(
0'
0)
b1100 !
b1100 %
1+
0#
#570
1#
#580
1(
b1101 !
b1101 %
1'
0#
#590
1#
#600
0(
0'
b1110 !
b1110 %
1)
0#
#610
1#
#620
1,
1*
1(
b1111 !
b1111 %
1'
0#
#630
1#
#640
0*
0,
0(
0'
0)
0+
b0 !
b0 %
0-
0#
