Lab8/Q2/qb.v
module fourtosixteen(a,En,f);
	input [3:0] a;
	input En;
	output [15:0] f;
	wire [1:0] E;
	assign E[0] = En & ~a[3];
	assign E[1] = En & a[3];
	threetoeight stage0(a[2:0],E[0],f[7:0]);
	threetoeight stage1(a[2:0],E[1],f[15:8]);
endmodule

module threetoeight(a,En,f);
	input [2:0] a;
	input En;
	output reg [7:0] f;
	wire [1:0] E;
	assign E[0] = En & ~a[2];
	assign E[1] = En & a[2];
	integer i;
	always@(a,En)
	begin
		for(i=0;i<=8;i=i+1)
		begin
			if((a == i) && (En == 1))
				f[i] = 1;
			else
				f[i] = 0;
		end
	end		
endmodule

Lab8/Q3/qb_tb.v
`timescale 1ns/1ns
`include "qb.v"

module qb_tb();
reg [3:0] a;
reg En;
wire [15:0] f;

fourtosixteen f1(a,En,f);
initial
begin
	$dumpfile("qb_tb.vcd");
	$dumpvars(0,qb_tb);
	
	En=1'b1;
	a=4'd0; #20;
	a=4'd1; #20;
	a=4'd2; #20;
	a=4'd3; #20;
	a=4'd4; #20;
	a=4'd5; #20;
	a=4'd6; #20;
	a=4'd7; #20;
	a=4'd8; #20;
	a=4'd9; #20;
	a=4'd10; #20;
	a=4'd11; #20;
	a=4'd12; #20;
	a=4'd13; #20;
	a=4'd14; #20;
	a=4'd15; #20;
	
	$display("Test Complete");
end 
endmodule

Lab8/Q2/qb_tb.vcd
$date
	Thu Oct 20 10:03:35 2022
$end
$version
	Icarus Verilog
$end
$timescale
	1ns
$end
$scope module qb_tb $end
$var wire 16 ! f [15:0] $end
$var reg 1 " En $end
$var reg 4 # a [3:0] $end
$scope module f1 $end
$var wire 1 " En $end
$var wire 4 $ a [3:0] $end
$var wire 16 % f [15:0] $end
$var wire 2 & E [1:0] $end
$scope module stage0 $end
$var wire 1 ' En $end
$var wire 3 ( a [2:0] $end
$var wire 2 ) E [1:0] $end
$var reg 8 * f [7:0] $end
$var integer 32 + i [31:0] $end
$upscope $end
$scope module stage1 $end
$var wire 1 , En $end
$var wire 3 - a [2:0] $end
$var wire 2 . E [1:0] $end
$var reg 8 / f [7:0] $end
$var integer 32 0 i [31:0] $end
$upscope $end
$upscope $end
$upscope $end
$enddefinitions $end
#0
$dumpvars
b1001 0
b0 /
b0 .
b0 -
0,
b1001 +
b1 *
b1 )
b0 (
1'
b1 &
b1 %
b0 $
b0 #
1"
b1 !
$end
#20
b10 !
b10 %
b10 *
b1001 +
b1001 0
b1 (
b1 -
b1 #
b1 $
#40
b100 !
b100 %
b100 *
b1001 +
b1001 0
b10 (
b10 -
b10 #
b10 $
#60
b1000 !
b1000 %
b1000 *
b1001 +
b1001 0
b11 (
b11 -
b11 #
b11 $
#80
b10 )
b10000 !
b10000 %
b10000 *
b1001 +
b1001 0
b100 (
b100 -
b100 #
b100 $
#100
b100000 !
b100000 %
b100000 *
b1001 +
b1001 0
b101 (
b101 -
b101 #
b101 $
#120
b1000000 !
b1000000 %
b1000000 *
b1001 +
b1001 0
b110 (
b110 -
b110 #
b110 $
#140
b10000000 !
b10000000 %
b10000000 *
b1001 +
b1001 0
b111 (
b111 -
b111 #
b111 $
#160
0'
b1 /
b1 .
1,
b0 )
b10 &
b100000000 !
b100000000 %
b0 *
b1001 +
b1001 0
b0 (
b0 -
b1000 #
b1000 $
#180
b1001 +
b1000000000 !
b1000000000 %
b10 /
b1001 0
b1 (
b1 -
b1001 #
b1001 $
#200
b1001 +
b10000000000 !
b10000000000 %
b100 /
b1001 0
b10 (
b10 -
b1010 #
b1010 $
#220
b1001 +
b100000000000 !
b100000000000 %
b1000 /
b1001 0
b11 (
b11 -
b1011 #
b1011 $
#240
b10 .
b1001 +
b1000000000000 !
b1000000000000 %
b10000 /
b1001 0
b100 (
b100 -
b1100 #
b1100 $
#260
b1001 +
b10000000000000 !
b10000000000000 %
b100000 /
b1001 0
b101 (
b101 -
b1101 #
b1101 $
#280
b1001 +
b100000000000000 !
b100000000000000 %
b1000000 /
b1001 0
b110 (
b110 -
b1110 #
b1110 $
#300
b1001 +
b1000000000000000 !
b1000000000000000 %
b10000000 /
b1001 0
b111 (
b111 -
b1111 #
b1111 $
