Lab8/Q4/qb.v
module encoder4to2(a,f);
	input [3:0] a;
	output reg [2:0] f;
	always @(a)
	begin
		casex(a)
		4'b0000: f=3'bzz0;
		4'b0001: f=3'b001;
		4'b001x: f=3'b011;
		4'b01xx: f=3'b101;
		4'b1xxx: f=3'b111;
		endcase
	end
endmodule

Lab8/Q5/qb_tb.v
`timescale 1ns/1ns
`include "qb.v"

module qb_tb();
reg [3:0] a;
wire [2:0] f;

encoder4to2 f1(a,f);
initial
begin
	$dumpfile("qb_tb.vcd");
	$dumpvars(0,qb_tb);
	
	a=4'd0; #20;
	a=4'd1; #20;
	a=4'd2; #20;
	a=4'd3; #20;
	a=4'd4; #20;
	a=4'd5; #20;
	a=4'd6; #20;
	a=4'd7; #20;
	a=4'd8; #20;
	a=4'd9; #20;
	a=4'd10; #20;
	a=4'd11; #20;
	a=4'd12; #20;
	a=4'd13; #20;
	a=4'd14; #20;
	a=4'd15; #20;
	
	$display("Test Complete");
end 
endmodule

Lab8/Q4/qb_tb.vcd
$date
	Thu Oct 20 10:54:23 2022
$end
$version
	Icarus Verilog
$end
$timescale
	1ns
$end
$scope module qb_tb $end
$var wire 3 ! f [2:0] $end
$var reg 4 " a [3:0] $end
$scope module f1 $end
$var wire 4 # a [3:0] $end
$var reg 3 $ f [2:0] $end
$upscope $end
$upscope $end
$enddefinitions $end
#0
$dumpvars
bz0 $
b0 #
b0 "
bz0 !
$end
#20
b1 !
b1 $
b1 "
b1 #
#40
b11 !
b11 $
b10 "
b10 #
#60
b11 "
b11 #
#80
b101 !
b101 $
b100 "
b100 #
#100
b101 "
b101 #
#120
b110 "
b110 #
#140
b111 "
b111 #
#160
b111 !
b111 $
b1000 "
b1000 #
#180
b1001 "
b1001 #
#200
b1010 "
b1010 #
#220
b1011 "
b1011 #
#240
b1100 "
b1100 #
#260
b1101 "
b1101 #
#280
b1110 "
b1110 #
#300
b1111 "
b1111 #
