Lab4/Q1/qb.v
module halfadder(x0,y0,cout0,sum0);
	input x0,y0;
	output cout0,sum0;
	assign sum0 = x0 ^ y0;
	assign cout0 = x0&y0;
endmodule

module fulladder(x1,y1,cin1,cout1,sum1);
	input x1,y1,cin1;
	output cout1,sum1;
	assign sum1 = x1 ^ y1 ^ cin1;
	assign cout1 = (x1&y1) | (x1&cin1) | (y1&cin1);
endmodule

module decomfulladd(x2,y2,cin2,cout2,sum2);
	input x2,y2,cin2;
	output cout2,sum2;
	halfadder stage0 (x2,y2,c1,s1);
	halfadder stage1 (s1,cin2,c2,sum2);
	assign cout2 = c1 | c2;
endmodule

Lab4/Q1/qb3_tb.v
`timescale 1ns/1ns
`include "qb.v"
module qb3_tb();
reg x2,y2,cin2;
wire cout2,sum2;

decomfulladd d1 (x2,y2,cin2,cout2,sum2);
initial
begin
$dumpfile("qb3_tb.vcd");
$dumpvars(0, qb3_tb);

x2 =  1'b0; y2 = 1'b0; cin2 =1'b0; #20;
x2 =  1'b0; y2 = 1'b0; cin2 =1'b1; #20;
x2 =  1'b0; y2 = 1'b1; cin2 =1'b0; #20;
x2 =  1'b0; y2 = 1'b1; cin2 =1'b1; #20;
x2 =  1'b1; y2 = 1'b0; cin2 =1'b0; #20;
x2 =  1'b1; y2 = 1'b0; cin2 =1'b1; #20;
x2 =  1'b1; y2 = 1'b1; cin2 =1'b0; #20;
x2 =  1'b1; y2 = 1'b1; cin2 =1'b1; #20;


$display("Test Completed");
end 
endmodule

Lab4/Q1/qb3_tb.vcd
$date
	Thu Sep 15 09:38:14 2022
$end
$version
	Icarus Verilog
$end
$timescale
	1ns
$end
$scope module qb3_tb $end
$var wire 1 ! sum2 $end
$var wire 1 " cout2 $end
$var reg 1 # cin2 $end
$var reg 1 $ x2 $end
$var reg 1 % y2 $end
$scope module d1 $end
$var wire 1 # cin2 $end
$var wire 1 " cout2 $end
$var wire 1 $ x2 $end
$var wire 1 % y2 $end
$var wire 1 ! sum2 $end
$var wire 1 & s1 $end
$var wire 1 ' c2 $end
$var wire 1 ( c1 $end
$scope module stage0 $end
$var wire 1 ( cout0 $end
$var wire 1 & sum0 $end
$var wire 1 $ x0 $end
$var wire 1 % y0 $end
$upscope $end
$scope module stage1 $end
$var wire 1 ' cout0 $end
$var wire 1 ! sum0 $end
$var wire 1 & x0 $end
$var wire 1 # y0 $end
$upscope $end
$upscope $end
$upscope $end
$enddefinitions $end
#0
$dumpvars
0(
0'
0&
0%
0$
0#
0"
0!
$end
#20
1!
1#
#40
1&
0#
1%
#60
1"
0!
1'
1#
#80
0"
1!
0'
0#
0%
1$
#100
1"
0!
1'
1#
#120
0'
0&
1(
0#
1%
#140
1!
1#
