Lab11/Q3/qb.v
module async4(clk,clear,Q);
	input clk,clear;
	output [3:0] Q;
	dff s0(~Q[0],clk,clear,Q[0]);
	dff s1(~Q[1],~Q[0],clear,Q[1]);
	dff s2(~Q[2],~Q[1],clear,Q[2]);
	dff s3(~Q[3],~Q[2],clear,Q[3]);
endmodule

module dff(D,clk,clear,Q);
	input D,clk,clear;
	output reg Q;
	always @(posedge clk or negedge clear)
	begin
	if(!clear)
		Q <= 0;
	else
		Q <= D;
	end
endmodule

Lab11/Q3/qb_tb.v
`timescale 1ns/1ns
`include "qb.v" 
module qb_tb();
reg clock,clear; 
wire [3:0] Q;
async4 r1(clock,clear,Q);
initial
begin
	$dumpfile("qb_tb.vcd");
	$dumpvars(0, qb_tb);
	clock=0;
	forever #20 clock = ~clock;
end
initial begin
	clear = 0; #40;
	clear = 1; #520;
	$display("Test complete");
	$finish;
	
end
endmodule

Lab11/Q3/qb_tb.vcd
$date
	Thu Nov 17 10:22:46 2022
$end
$version
	Icarus Verilog
$end
$timescale
	1ns
$end
$scope module qb_tb $end
$var wire 4 ! Q [3:0] $end
$var reg 1 " clear $end
$var reg 1 # clock $end
$scope module r1 $end
$var wire 1 " clear $end
$var wire 1 # clk $end
$var wire 4 $ Q [3:0] $end
$scope module s0 $end
$var wire 1 % D $end
$var wire 1 " clear $end
$var wire 1 # clk $end
$var reg 1 & Q $end
$upscope $end
$scope module s1 $end
$var wire 1 ' D $end
$var wire 1 " clear $end
$var wire 1 ( clk $end
$var reg 1 ) Q $end
$upscope $end
$scope module s2 $end
$var wire 1 * D $end
$var wire 1 " clear $end
$var wire 1 + clk $end
$var reg 1 , Q $end
$upscope $end
$scope module s3 $end
$var wire 1 - D $end
$var wire 1 " clear $end
$var wire 1 . clk $end
$var reg 1 / Q $end
$upscope $end
$upscope $end
$upscope $end
$enddefinitions $end
#0
$dumpvars
x/
x.
x-
x,
x+
x*
x)
x(
x'
x&
x%
bx $
0#
0"
bx !
$end
#20
1-
0/
1.
1*
0,
1+
1'
0)
1(
1%
b0 !
b0 $
0&
1#
#40
0#
1"
#60
0(
0%
b1 !
b1 $
1&
1#
#80
0#
#100
0+
0'
1)
1(
1%
b10 !
b10 $
0&
1#
#120
0#
#140
0(
0%
b11 !
b11 $
1&
1#
#160
0#
#180
0.
0*
1,
1+
1'
0)
1(
1%
b100 !
b100 $
0&
1#
#200
0#
#220
0(
0%
b101 !
b101 $
1&
1#
#240
0#
#260
0+
0'
1)
1(
1%
b110 !
b110 $
0&
1#
#280
0#
#300
0(
0%
b111 !
b111 $
1&
1#
#320
0#
#340
0-
1/
1.
1*
0,
1+
1'
0)
1(
1%
b1000 !
b1000 $
0&
1#
#360
0#
#380
0(
0%
b1001 !
b1001 $
1&
1#
#400
0#
#420
0+
0'
1)
1(
1%
b1010 !
b1010 $
0&
1#
#440
0#
#460
0(
0%
b1011 !
b1011 $
1&
1#
#480
0#
#500
0.
0*
1,
1+
1'
0)
1(
1%
b1100 !
b1100 $
0&
1#
#520
0#
#540
0(
0%
b1101 !
b1101 $
1&
1#
