Lab11/Q1/qb.v
module ringc(clk,clear,set,Q);
	input set,clk,clear;
	output [3:0] Q;
	dff s0(Q[0],clk,clear,set,Q[3]);
	dff s1(Q[3],clk,clear,~set,Q[2]);
	dff s2(Q[2],clk,clear,~set,Q[1]);
	dff s3(Q[1],clk,clear,~set,Q[0]);
endmodule

module dff(D,clk,clear,set,Q);
	input D,clk,set,clear;
	output reg Q;
	always @(posedge clk)
	begin
	if(!clear && set)
		Q <= 1;
	else if(!clear)
		Q <= 0;
	else
		Q <= D;
	end
endmodule

/*module twotofour(a,En,f);	
	input [1:0] a;
	input En;
	output reg [3:0] f;
	always@(a,En)
	begin
		case(a)
		0:4'd1;
		1:4'd2;
		2:4'd3;
		3:4'd4;
		default:4'd0;
		endcase
	end
endmodule
*/

Lab11/Q1/qb_tb.v
`timescale 1ns/1ns
`include "qb.v" 
module qb_tb();
reg clock, set,clear; 
wire [3:0] Q;
ringc r1(clock, clear,set, Q);
initial
begin
	$dumpfile("qb_tb.vcd");
	$dumpvars(0, qb_tb);
	clock=0;
	forever #20 clock = ~clock;
end
initial begin
	clear = 0; 
	set = 1; #40;
	set = 0;
	clear = 1;
	#320;
	$display("Test complete");
	$finish;
	
end
endmodule

Lab11/Q1/qb_tb.vcd
$date
	Thu Nov 17 09:43:43 2022
$end
$version
	Icarus Verilog
$end
$timescale
	1ns
$end
$scope module qb_tb $end
$var wire 4 ! Q [3:0] $end
$var reg 1 " clear $end
$var reg 1 # clock $end
$var reg 1 $ set $end
$scope module r1 $end
$var wire 1 " clear $end
$var wire 1 # clk $end
$var wire 1 $ set $end
$var wire 4 % Q [3:0] $end
$scope module s0 $end
$var wire 1 & D $end
$var wire 1 " clear $end
$var wire 1 # clk $end
$var wire 1 $ set $end
$var reg 1 ' Q $end
$upscope $end
$scope module s1 $end
$var wire 1 ( D $end
$var wire 1 " clear $end
$var wire 1 # clk $end
$var wire 1 ) set $end
$var reg 1 * Q $end
$upscope $end
$scope module s2 $end
$var wire 1 + D $end
$var wire 1 " clear $end
$var wire 1 # clk $end
$var wire 1 , set $end
$var reg 1 - Q $end
$upscope $end
$scope module s3 $end
$var wire 1 . D $end
$var wire 1 " clear $end
$var wire 1 # clk $end
$var wire 1 / set $end
$var reg 1 0 Q $end
$upscope $end
$upscope $end
$upscope $end
$enddefinitions $end
#0
$dumpvars
x0
0/
x.
x-
0,
x+
x*
0)
x(
x'
x&
bx %
1$
0#
0"
bx !
$end
#20
1(
0+
0.
0&
1'
0*
0-
b1000 !
b1000 %
00
1#
#40
1)
1,
1/
0#
1"
0$
#60
1+
0(
1*
b100 !
b100 %
0'
1#
#80
0#
#100
0+
1.
0*
b10 !
b10 %
1-
1#
#120
0#
#140
1&
0.
10
b1 !
b1 %
0-
1#
#160
0#
#180
1(
0&
1'
b1000 !
b1000 %
00
1#
#200
0#
#220
1+
0(
1*
b100 !
b100 %
0'
1#
#240
0#
#260
0+
1.
0*
b10 !
b10 %
1-
1#
#280
0#
#300
1&
0.
10
b1 !
b1 %
0-
1#
#320
0#
#340
1(
0&
1'
b1000 !
b1000 %
00
1#
