Lab2/Q1/Part-2/qb.v
module qb(A,B,C,D,f);
	input A,B,C,D;
	output f;
	assign f = (B&~C&~D) | (~B&D) | (~B&C);
endmodule

Lab2/Q2/Part-2/qb_tb.v
`timescale 1ns/1ns
`include "qb.v"

module qb_tb();
reg A,B,C,D;
wire f;

qb qb(A,B,C,D,f);
initial
begin
	$dumpfile("qb_tb.vcd");
	$dumpvars(0,qb_tb);
	
	A = 1'b0; B =1'b0; C =1'b0; D =1'b0;
	#20;
	
	A = 1'b0; B =1'b0; C =1'b0; D =1'b1;
	#20;
	
	A = 1'b0; B =1'b0; C =1'b1; D =1'b0;
	#20;
	
	A = 1'b0; B =1'b0; C =1'b1; D =1'b1;
	#20;
	
	A = 1'b0; B =1'b1; C =1'b0; D =1'b0;
	#20;
	
	A = 1'b0; B =1'b1; C =1'b0; D =1'b1;
	#20;
	
	A = 1'b0; B =1'b1; C =1'b1; D =1'b0;
	#20;
	
	A = 1'b0; B =1'b1; C =1'b1; D =1'b1;
	#20;
	
	A = 1'b1; B =1'b0; C =1'b0; D =1'b0;
	#20;
	
	A = 1'b1; B =1'b0; C =1'b0; D =1'b1;
	#20;
	
	A = 1'b1; B =1'b0; C =1'b1; D =1'b0;
	#20;
	
	A = 1'b1; B =1'b0; C =1'b1; D =1'b1;
	#20;
	
	A = 1'b1; B =1'b1; C =1'b0; D =1'b0;
	#20;
	
	A = 1'b1; B =1'b1; C =1'b0; D =1'b1;
	#20;
	
	A = 1'b1; B =1'b1; C =1'b1; D =1'b0;
	#20;
	
	A = 1'b1; B =1'b1; C =1'b1; D =1'b1;
	#20;
	
	$display("Test Complete");
end

endmodule

Lab2/Q1/Part-2/qb_tb.vcd
$date
	Thu Sep  1 09:55:26 2022
$end
$version
	Icarus Verilog
$end
$timescale
	1ns
$end
$scope module qb_tb $end
$var wire 1 ! f $end
$var reg 1 " A $end
$var reg 1 # B $end
$var reg 1 $ C $end
$var reg 1 % D $end
$scope module qb $end
$var wire 1 " A $end
$var wire 1 # B $end
$var wire 1 $ C $end
$var wire 1 % D $end
$var wire 1 ! f $end
$upscope $end
$upscope $end
$enddefinitions $end
#0
$dumpvars
0%
0$
0#
0"
0!
$end
#20
1!
1%
#40
0%
1$
#60
1%
#80
1!
0%
0$
1#
#100
0!
1%
#120
0%
1$
#140
1%
#160
0%
0$
0#
1"
#180
1!
1%
#200
0%
1$
#220
1%
#240
1!
0%
0$
1#
#260
0!
1%
#280
0%
1$
#300
1%
