Lab3/Q3/qb.v
module qb(x1,x2,x3,x4,x5,f);
	input x1,x2,x3,x4,x5;
	output f;
	assign g = x5 & (~x1|x2);
	assign f = (g&x3&x4) | (g&~x3&~x4) | (~g&~x3&x4);
endmodule

Lab3/Q3/qb_tb.v
`timescale 1ns/1ns
`include "qb.v"

module qb_tb();
reg x1,x2,x3,x4,x5;
wire f;

qb qb(x1,x2,x3,x4,x5,f);
initial
begin
	$dumpfile("qb_tb.vcd");
	$dumpvars(0,qb_tb);
	
	x1=1'b0; x2=1'b0; x3=1'b0; x4=1'b0; x5=1'b0; #20;
	x1=1'b0; x2=1'b0; x3=1'b0; x4=1'b0; x5=1'b1; #20;
	x1=1'b0; x2=1'b0; x3=1'b0; x4=1'b1; x5=1'b0; #20;
	x1=1'b0; x2=1'b0; x3=1'b0; x4=1'b1; x5=1'b1; #20;
	x1=1'b0; x2=1'b0; x3=1'b1; x4=1'b0; x5=1'b0; #20;
	x1=1'b0; x2=1'b0; x3=1'b1; x4=1'b0; x5=1'b1; #20;
	x1=1'b0; x2=1'b0; x3=1'b1; x4=1'b1; x5=1'b0; #20;
	x1=1'b0; x2=1'b0; x3=1'b1; x4=1'b1; x5=1'b1; #20;
	x1=1'b0; x2=1'b1; x3=1'b0; x4=1'b0; x5=1'b0; #20;
	x1=1'b0; x2=1'b1; x3=1'b0; x4=1'b0; x5=1'b1; #20;
	x1=1'b0; x2=1'b1; x3=1'b0; x4=1'b1; x5=1'b0; #20;
	x1=1'b0; x2=1'b1; x3=1'b0; x4=1'b1; x5=1'b1; #20;
	x1=1'b0; x2=1'b1; x3=1'b1; x4=1'b0; x5=1'b0; #20;
	x1=1'b0; x2=1'b1; x3=1'b1; x4=1'b0; x5=1'b1; #20;
	x1=1'b0; x2=1'b1; x3=1'b1; x4=1'b1; x5=1'b0; #20;
	x1=1'b0; x2=1'b1; x3=1'b1; x4=1'b1; x5=1'b1; #20;
	x1=1'b1; x2=1'b0; x3=1'b0; x4=1'b0; x5=1'b0; #20;
	x1=1'b1; x2=1'b0; x3=1'b0; x4=1'b0; x5=1'b1; #20;
	x1=1'b1; x2=1'b0; x3=1'b0; x4=1'b1; x5=1'b0; #20;
	x1=1'b1; x2=1'b0; x3=1'b0; x4=1'b1; x5=1'b1; #20;
	x1=1'b1; x2=1'b0; x3=1'b1; x4=1'b0; x5=1'b0; #20;
	x1=1'b1; x2=1'b0; x3=1'b1; x4=1'b0; x5=1'b1; #20;
	x1=1'b1; x2=1'b0; x3=1'b1; x4=1'b1; x5=1'b0; #20;
	x1=1'b1; x2=1'b0; x3=1'b1; x4=1'b1; x5=1'b1; #20;
	x1=1'b1; x2=1'b1; x3=1'b0; x4=1'b0; x5=1'b0; #20;
	x1=1'b1; x2=1'b1; x3=1'b0; x4=1'b0; x5=1'b1; #20;
	x1=1'b1; x2=1'b1; x3=1'b0; x4=1'b1; x5=1'b0; #20;
	x1=1'b1; x2=1'b1; x3=1'b0; x4=1'b1; x5=1'b1; #20;
	x1=1'b1; x2=1'b1; x3=1'b1; x4=1'b0; x5=1'b0; #20;
	x1=1'b1; x2=1'b1; x3=1'b1; x4=1'b0; x5=1'b1; #20;
	x1=1'b1; x2=1'b1; x3=1'b1; x4=1'b1; x5=1'b0; #20;
	x1=1'b1; x2=1'b1; x3=1'b1; x4=1'b1; x5=1'b1; #20;
	$display("Test Complete");
end

endmodule

Lab3/Q3/qb_tb.vcd
$date
	Thu Sep  8 10:54:14 2022
$end
$version
	Icarus Verilog
$end
$timescale
	1ns
$end
$scope module qb_tb $end
$var wire 1 ! f $end
$var reg 1 " x1 $end
$var reg 1 # x2 $end
$var reg 1 $ x3 $end
$var reg 1 % x4 $end
$var reg 1 & x5 $end
$scope module qb $end
$var wire 1 ! f $end
$var wire 1 ' g $end
$var wire 1 " x1 $end
$var wire 1 # x2 $end
$var wire 1 $ x3 $end
$var wire 1 % x4 $end
$var wire 1 & x5 $end
$upscope $end
$upscope $end
$enddefinitions $end
#0
$dumpvars
0'
0&
0%
0$
0#
0"
0!
$end
#20
1!
1'
1&
#40
1!
0'
0&
1%
#60
0!
1'
1&
#80
0'
0&
0%
1$
#100
1'
1&
#120
0!
0'
0&
1%
#140
1!
1'
1&
#160
0!
0'
0&
0%
0$
1#
#180
1!
1'
1&
#200
1!
0'
0&
1%
#220
0!
1'
1&
#240
0'
0&
0%
1$
#260
1'
1&
#280
0!
0'
0&
1%
#300
1!
1'
1&
#320
0!
0'
0&
0%
0$
0#
1"
#340
1&
#360
1!
0&
1%
#380
1&
#400
0!
0&
0%
1$
#420
1&
#440
0&
1%
#460
1&
#480
0&
0%
0$
1#
#500
1!
1'
1&
#520
1!
0'
0&
1%
#540
0!
1'
1&
#560
0'
0&
0%
1$
#580
1'
1&
#600
0!
0'
0&
1%
#620
1!
1'
1&
